hibachi_xyz/__init__.py
hibachi_xyz/api.py
hibachi_xyz/api_ws_account.py
hibachi_xyz/api_ws_market.py
hibachi_xyz/api_ws_trade.py
hibachi_xyz/env_setup.py
hibachi_xyz/helpers.py
hibachi_xyz/types.py
hibachi_xyz-0.1.14.dist-info/licenses/LICENSE
hibachi_xyz-0.1.14.dist-info/METADATA
hibachi_xyz-0.1.14.dist-info/WHEEL
hibachi_xyz-0.1.14.dist-info/top_level.txt
hibachi_xyz-0.1.14.dist-info/RECORD
