Metadata-Version: 2.4
Name: hibachi_xyz
Version: 0.1.14
Summary: Hibachi SDK for accessing the API
Author: Hibachi Engineer
License-Expression: MIT
Project-URL: Homepage, https://github.com/hibachi-xyz/yule-os
Project-URL: Issues, https://github.com/hibachi-xyz/yule-os/issues
Requires-Python: <4,>=3.13
License-File: LICENSE
Requires-Dist: eth_keys==0.6.1
Requires-Dist: requests==2.32.3
Requires-Dist: toml==0.10.2
Requires-Dist: websockets>=11.0.3
Requires-Dist: python-dotenv>=1.0.0
Requires-Dist: prettyprinter>=0.18.0
Requires-Dist: pip-system-certs
Provides-Extra: dev
Requires-Dist: pytest; extra == "dev"
Requires-Dist: pytest-asyncio; extra == "dev"
Requires-Dist: pytest-timeout; extra == "dev"
Dynamic: license-file
